EzGM/__init__.py
EzGM/selection.py
EzGM/signal.py
EzGM/utility.py
EzGM/webdriverdownloader.py
EzGM-1.7.0.2.dist-info/LICENSE
EzGM-1.7.0.2.dist-info/METADATA
EzGM-1.7.0.2.dist-info/WHEEL
EzGM-1.7.0.2.dist-info/top_level.txt
EzGM-1.7.0.2.dist-info/RECORD
