Metadata-Version: 2.1
Name: EzGM
Version: 1.7.0.2
Summary: Toolbox for ground motion record selection and processing
Home-page: https://github.com/volkanozsarac/EzGM
Author: Volkan Ozsarac
Author-email: volkan.ozsarac@iusspavia.it
Project-URL: Bug Tracker, https://github.com/volkanozsarac/EzGM/issues
Classifier: Programming Language :: Python :: 3.8
Classifier: Programming Language :: Python :: 3.9
Classifier: License :: OSI Approved :: GNU General Public License v3 (GPLv3)
Classifier: Operating System :: OS Independent
Requires-Python: >3.7
License-File: LICENSE
Requires-Dist: openquake.engine >=3.14.0
Requires-Dist: selenium ==4.2.0
Requires-Dist: numba >=0.55.1
Requires-Dist: beautifulsoup4 >=4.11.1
Requires-Dist: tqdm >=4.64.0
Requires-Dist: h5py >=3.1.0
Requires-Dist: matplotlib >=3.1.2
